LICENSE
README.md
setup.cfg
setup.py
jcopml/__init__.py
jcopml.egg-info/PKG-INFO
jcopml.egg-info/SOURCES.txt
jcopml.egg-info/dependency_links.txt
jcopml.egg-info/requires.txt
jcopml.egg-info/top_level.txt
jcopml/automl/__init__.py
jcopml/automl/_automl.py
jcopml/automl/_automl_params.py
jcopml/feature_importance/__init__.py
jcopml/feature_importance/_mean_loss_decrease.py
jcopml/feature_importance/_mean_score_decrease.py
jcopml/pipeline/__init__.py
jcopml/pipeline/_pipeline.py
jcopml/plot/__init__.py
jcopml/plot/_actual_vs_prediction.py
jcopml/plot/_association_matrix.py
jcopml/plot/_classification_report.py
jcopml/plot/_confusion_matrix.py
jcopml/plot/_correlation_matrix.py
jcopml/plot/_correlation_ratio.py
jcopml/plot/_missing_value.py
jcopml/plot/_pr_curve.py
jcopml/plot/_residual_plot.py
jcopml/plot/_roc_curve.py
jcopml/plot/_svc_decision.py
jcopml/snippets/__init__.py
jcopml/snippets/const.py
jcopml/snippets/widget.py
jcopml/time_series/__init__.py
jcopml/time_series/arima.py
jcopml/time_series/decomposition.py
jcopml/time_series/ets.py
jcopml/time_series/frequencies.py
jcopml/time_series/io.py
jcopml/time_series/metric.py
jcopml/time_series/plot.py
jcopml/time_series/utils.py
jcopml/time_series/warnings.py
jcopml/tuning/__init__.py
jcopml/tuning/_bayes_search.py
jcopml/tuning/_grid_search.py
jcopml/tuning/_random_search.py
jcopml/tuning/skopt.py
jcopml/tuning/space.py
jcopml/utils/__init__.py
jcopml/utils/_load_model.py
jcopml/utils/_save_model.py