Metadata-Version: 2.1
Name: jcopml
Version: 1.2.6
Summary: J.COp ML is a machine Learning package to complement scikit-learn workflow
Home-page: https://github.com/WiraDKP/jcopml
Author: Wira Dharma Kencana Putra
Author-email: wiradharma_kencanaputra@yahoo.com
Keywords: machine learning ml jcop indonesia
Classifier: Programming Language :: Python :: 3.6
Classifier: Intended Audience :: Developers
Classifier: Intended Audience :: Education
Classifier: Intended Audience :: Information Technology
Classifier: Intended Audience :: Science/Research
Classifier: Topic :: Scientific/Engineering :: Artificial Intelligence
Classifier: Natural Language :: Indonesian
Classifier: Natural Language :: English
Requires-Python: >=3.6.6
License-File: LICENSE
Requires-Dist: numpy
Requires-Dist: scipy
Requires-Dist: pandas
Requires-Dist: scikit-learn
Requires-Dist: matplotlib
Requires-Dist: seaborn
Requires-Dist: scikit-optimize
Requires-Dist: ipywidgets
Requires-Dist: statsmodels
Requires-Dist: pyperclip
